odoo/addons/crm_lead_search_archive/README.rst
odoo/addons/crm_lead_search_archive/__init__.py
odoo/addons/crm_lead_search_archive/__manifest__.py
odoo/addons/crm_lead_search_archive/i18n/crm_lead_search_archive.pot
odoo/addons/crm_lead_search_archive/i18n/es.po
odoo/addons/crm_lead_search_archive/i18n/fr.po
odoo/addons/crm_lead_search_archive/i18n/it.po
odoo/addons/crm_lead_search_archive/readme/CONTRIBUTORS.rst
odoo/addons/crm_lead_search_archive/readme/DESCRIPTION.rst
odoo/addons/crm_lead_search_archive/static/description/icon.png
odoo/addons/crm_lead_search_archive/static/description/index.html
odoo/addons/crm_lead_search_archive/views/crm_lead_view.xml
odoo_addon_crm_lead_search_archive-16.0.1.0.1.5.dist-info/METADATA
odoo_addon_crm_lead_search_archive-16.0.1.0.1.5.dist-info/WHEEL
odoo_addon_crm_lead_search_archive-16.0.1.0.1.5.dist-info/top_level.txt
odoo_addon_crm_lead_search_archive-16.0.1.0.1.5.dist-info/RECORD
